exchange_log_handler/__init__.py
exchange_log_handler-0.1.0.dist-info/LICENSE
exchange_log_handler-0.1.0.dist-info/METADATA
exchange_log_handler-0.1.0.dist-info/WHEEL
exchange_log_handler-0.1.0.dist-info/top_level.txt
exchange_log_handler-0.1.0.dist-info/RECORD
