Metadata-Version: 2.1
Name: exchange-log-handler
Version: 0.1.0
Summary: Log handler to send log via exchange.
Home-page: https://github.com/parklam/exchange_log_handler
Author: Park Lam
Author-email: lqmonline@gmail.com
License: Apache License 2.0
Keywords: log handler exchange
Platform: UNKNOWN
Classifier: Programming Language :: Python :: 3
Classifier: License :: OSI Approved :: Apache Software License
Classifier: Operating System :: OS Independent
Requires-Dist: exchangelib (==2.1.1)
